krec-0.3.1.dist-info/top_level.txt
krec-0.3.1.dist-info/RECORD
krec-0.3.1.dist-info/LICENSE
krec-0.3.1.dist-info/METADATA
krec-0.3.1.dist-info/WHEEL
krec/requirements-dev.txt
krec/requirements.txt
krec/__init__.py
krec/bindings.pyi
krec/bindings.cpython-311-aarch64-linux-gnu.so
krec/py.typed
krec/bindings/pyproject.toml
krec/bindings/Cargo.toml
krec/bindings/src/lib.rs
krec/bindings/src/bin/stub_gen.rs
