Metadata-Version: 2.1
Name: krec
Version: 0.3.1
Summary: Python bindings for K-Scale recordings
Home-page: https://github.com/kscalelabs/krec
Author: K-Scale Labs
Requires-Python: >=3.8
License-File: LICENSE
Requires-Dist: colorlogging
Provides-Extra: dev
Requires-Dist: black; extra == "dev"
Requires-Dist: isort; extra == "dev"
Requires-Dist: ruff; extra == "dev"
Requires-Dist: mypy; extra == "dev"
Requires-Dist: pytest; extra == "dev"
